djalog
