Metadata-Version: 1.0
Name: Djalog
Version: 0.9.4
Summary: 
